smartcoop/__init__.py
smartcoop/client.py
smartcoop/api/__init__.py
smartcoop/api/omlet.py
smartcoop/api/models/__init__.py
smartcoop/api/models/action.py
smartcoop/api/models/configuration.py
smartcoop/api/models/configuration_connectivity.py
smartcoop/api/models/configuration_door.py
smartcoop/api/models/configuration_feeder.py
smartcoop/api/models/configuration_general.py
smartcoop/api/models/configuration_light.py
smartcoop/api/models/device.py
smartcoop/api/models/group.py
smartcoop/api/models/group_subset.py
smartcoop/api/models/state.py
smartcoop/api/models/state_connectivity.py
smartcoop/api/models/state_door.py
smartcoop/api/models/state_feeder.py
smartcoop/api/models/state_general.py
smartcoop/api/models/state_light.py
smartcoop/api/models/user.py
smartcoop_python_sdk-0.1.3.dist-info/METADATA
smartcoop_python_sdk-0.1.3.dist-info/WHEEL
smartcoop_python_sdk-0.1.3.dist-info/top_level.txt
smartcoop_python_sdk-0.1.3.dist-info/RECORD
