Metadata-Version: 2.4
Name: smartcoop-python-sdk
Version: 0.1.3
Summary: A Python SDK for the SmartCoop API
Home-page: https://github.com/Omlet-Ltd/smartcoop-python-sdk
Author: Omlet
Author-email: info@omlet.com
Classifier: Programming Language :: Python :: 3
Classifier: License :: OSI Approved :: MIT License
Classifier: Operating System :: OS Independent
Requires-Python: >=3.6
Requires-Dist: requests
Dynamic: author
Dynamic: author-email
Dynamic: classifier
Dynamic: description
Dynamic: description-content-type
Dynamic: home-page
Dynamic: requires-dist
Dynamic: requires-python
Dynamic: summary
